pyqttier/__init__.py
pyqttier/connection.py
pyqttier/interface.py
pyqttier/lwt.py
pyqttier/message.py
pyqttier/mock.py
pyqttier/py.typed
pyqttier/transport.py
pyqttier-0.2.5.dist-info/METADATA
pyqttier-0.2.5.dist-info/WHEEL
pyqttier-0.2.5.dist-info/licenses/LICENSE
pyqttier-0.2.5.dist-info/RECORD
