Metadata-Version: 2.4
Name: pyqttier
Version: 0.2.5
Summary: Convenient wrapper around Paho MQTT
Author-email: Jacob Brunson <github@jacobbrunson.com>
License-File: LICENSE
Requires-Python: >=3.7
Requires-Dist: paho-mqtt>=2.1.0
